sql_translator/__init__.py
sql_translator/sql.py
sql_translator-0.1.1.dist-info/METADATA
sql_translator-0.1.1.dist-info/WHEEL
sql_translator-0.1.1.dist-info/RECORD
